intradev/FileEntry.py
intradev/FileOutput.py
intradev/__init__.py
intradev/util.py
intradev-0.1.1.dist-info/METADATA
intradev-0.1.1.dist-info/WHEEL
intradev-0.1.1.dist-info/licenses/LICENSE.txt
intradev-0.1.1.dist-info/RECORD
