Metadata-Version: 2.4
Name: intradev
Version: 0.1.1
Summary: tool to accelerate creation of simple IO Python GUIs.
Project-URL: Homepage, https://github.com/asm3002/intradev
Project-URL: Issues, https://github.com/asm3002/intradev/issues
Author-email: Aiden McDougal <lilsteeler03@gmail.com>
License-File: LICENSE.txt
Classifier: License :: OSI Approved :: MIT License
Classifier: Operating System :: OS Independent
Classifier: Programming Language :: Python :: 3
Requires-Python: >=3.0
Requires-Dist: customtkinter>=5.2
